kubernetes_asyncio_pydantic/__init__.py
kubernetes_asyncio_pydantic/api/__init__.py
kubernetes_asyncio_pydantic/api/admissionregistration_api.py
kubernetes_asyncio_pydantic/api/admissionregistration_v1_api.py
kubernetes_asyncio_pydantic/api/admissionregistration_v1alpha1_api.py
kubernetes_asyncio_pydantic/api/admissionregistration_v1beta1_api.py
kubernetes_asyncio_pydantic/api/apiextensions_api.py
kubernetes_asyncio_pydantic/api/apiextensions_v1_api.py
kubernetes_asyncio_pydantic/api/apiregistration_api.py
kubernetes_asyncio_pydantic/api/apiregistration_v1_api.py
kubernetes_asyncio_pydantic/api/apis_api.py
kubernetes_asyncio_pydantic/api/apps_api.py
kubernetes_asyncio_pydantic/api/apps_v1_api.py
kubernetes_asyncio_pydantic/api/authentication_api.py
kubernetes_asyncio_pydantic/api/authentication_v1_api.py
kubernetes_asyncio_pydantic/api/authorization_api.py
kubernetes_asyncio_pydantic/api/authorization_v1_api.py
kubernetes_asyncio_pydantic/api/autoscaling_api.py
kubernetes_asyncio_pydantic/api/autoscaling_v1_api.py
kubernetes_asyncio_pydantic/api/autoscaling_v2_api.py
kubernetes_asyncio_pydantic/api/batch_api.py
kubernetes_asyncio_pydantic/api/batch_v1_api.py
kubernetes_asyncio_pydantic/api/certificates_api.py
kubernetes_asyncio_pydantic/api/certificates_v1_api.py
kubernetes_asyncio_pydantic/api/certificates_v1alpha1_api.py
kubernetes_asyncio_pydantic/api/certificates_v1beta1_api.py
kubernetes_asyncio_pydantic/api/coordination_api.py
kubernetes_asyncio_pydantic/api/coordination_v1_api.py
kubernetes_asyncio_pydantic/api/coordination_v1alpha2_api.py
kubernetes_asyncio_pydantic/api/coordination_v1beta1_api.py
kubernetes_asyncio_pydantic/api/core_api.py
kubernetes_asyncio_pydantic/api/core_v1_api.py
kubernetes_asyncio_pydantic/api/discovery_api.py
kubernetes_asyncio_pydantic/api/discovery_v1_api.py
kubernetes_asyncio_pydantic/api/events_api.py
kubernetes_asyncio_pydantic/api/events_v1_api.py
kubernetes_asyncio_pydantic/api/flowcontrol_apiserver_api.py
kubernetes_asyncio_pydantic-1.34.1.dist-info/METADATA
kubernetes_asyncio_pydantic-1.34.1.dist-info/WHEEL
kubernetes_asyncio_pydantic-1.34.1.dist-info/RECORD
