Metadata-Version: 2.4
Name: kubernetes_asyncio_pydantic
Version: 1.34.1
Summary: async Kubernetes client with Pydantic support
License-Expression: MIT
Keywords: OpenAPI,OpenAPI-Generator,Kubernetes
Author: Partho Bhowmick
Author-email: partho.bhowmick@icloud.com
Requires-Python: >=3.13,<4.0
Classifier: Programming Language :: Python :: 3
Classifier: Programming Language :: Python :: 3.13
Classifier: Programming Language :: Python :: 3.14
Requires-Dist: aiohttp (>=3.8.4)
Requires-Dist: aiohttp-retry (>=2.8.3)
Requires-Dist: lazy-imports (>=1.0.1)
Requires-Dist: pydantic (>=2,<3)
Requires-Dist: python-dateutil (>=2.8.2)
Requires-Dist: typing-extensions (>=4.7.1)
Requires-Dist: urllib3 (>=1.25.3,<3.0.0)
